web_archive_api/__init__.py
web_archive_api/cdx.py
web_archive_api/memento.py
web_archive_api/test_memento.py
web_archive_api/warc.py
web_archive_api-1.1.0.dist-info/LICENSE
web_archive_api-1.1.0.dist-info/METADATA
web_archive_api-1.1.0.dist-info/WHEEL
web_archive_api-1.1.0.dist-info/top_level.txt
web_archive_api-1.1.0.dist-info/RECORD
