Metadata-Version: 2.2
Name: web-archive-api
Version: 1.1.0
Summary: Unified, type-safe access to web archive APIs.
Author-email: Jan Heinrich Merker <heinrich.merker@uni-jena.de>
Project-URL: Homepage, https://github.com/janheinrichmerker/web-archive-api
Project-URL: Bug Tracker, https://github.com/janheinrichmerker/web-archive-api/issues
Classifier: Programming Language :: Python :: 3
Classifier: Programming Language :: Python :: 3 :: Only
Classifier: Programming Language :: Python :: 3.8
Classifier: Programming Language :: Python :: 3.9
Classifier: Programming Language :: Python :: 3.10
Classifier: Programming Language :: Python :: 3.11
Classifier: License :: OSI Approved :: MIT License
Classifier: Operating System :: OS Independent
Classifier: Intended Audience :: Science/Research
Classifier: Topic :: Scientific/Engineering
Requires-Python: >=3.8
License-File: LICENSE
Requires-Dist: importlib-metadata<9.0,>=6.5
Requires-Dist: requests~=2.28
Requires-Dist: tqdm~=4.64
Requires-Dist: warcio~=1.7
Provides-Extra: tests
Requires-Dist: bandit[toml]~=1.7; extra == "tests"
Requires-Dist: mypy~=1.6; extra == "tests"
Requires-Dist: pytest<9.0,>=7.2; extra == "tests"
Requires-Dist: pytest-cov<7,>=4; extra == "tests"
Requires-Dist: ruff~=0.2.1; extra == "tests"
Requires-Dist: types-requests~=2.31; extra == "tests"
Requires-Dist: types-tqdm~=4.66; extra == "tests"
